<annotation>
	<folder></folder>
	<filename>000077--2-_JPG_jpg.rf.e01293713a0cd6a291204c1e56c702d2.jpg</filename>
	<path>000077--2-_JPG_jpg.rf.e01293713a0cd6a291204c1e56c702d2.jpg</path>
	<source>
		<database>roboflow.ai</database>
	</source>
	<size>
		<width>416</width>
		<height>416</height>
		<depth>3</depth>
	</size>
	<segmented>0</segmented>
	<object>
		<name>plastik</name>
		<pose>Unspecified</pose>
		<truncated>0</truncated>
		<difficult>0</difficult>
		<occluded>0</occluded>
		<bndbox>
			<xmin>91</xmin>
			<xmax>141</xmax>
			<ymin>191</ymin>
			<ymax>254</ymax>
		</bndbox>
	</object>
</annotation>
