<annotation>
	<folder></folder>
	<filename>000024--4-_JPG_jpg.rf.7d997a2c1f9d04342bd034b28dc089e2.jpg</filename>
	<path>000024--4-_JPG_jpg.rf.7d997a2c1f9d04342bd034b28dc089e2.jpg</path>
	<source>
		<database>roboflow.ai</database>
	</source>
	<size>
		<width>416</width>
		<height>416</height>
		<depth>3</depth>
	</size>
	<segmented>0</segmented>
	<object>
		<name>metal</name>
		<pose>Unspecified</pose>
		<truncated>0</truncated>
		<difficult>0</difficult>
		<occluded>0</occluded>
		<bndbox>
			<xmin>144</xmin>
			<xmax>178</xmax>
			<ymin>252</ymin>
			<ymax>297</ymax>
		</bndbox>
	</object>
	<object>
		<name>metal</name>
		<pose>Unspecified</pose>
		<truncated>0</truncated>
		<difficult>0</difficult>
		<occluded>0</occluded>
		<bndbox>
			<xmin>182</xmin>
			<xmax>216</xmax>
			<ymin>193</ymin>
			<ymax>234</ymax>
		</bndbox>
	</object>
	<object>
		<name>karton</name>
		<pose>Unspecified</pose>
		<truncated>0</truncated>
		<difficult>0</difficult>
		<occluded>0</occluded>
		<bndbox>
			<xmin>222</xmin>
			<xmax>286</xmax>
			<ymin>181</ymin>
			<ymax>245</ymax>
		</bndbox>
	</object>
</annotation>
