<annotation>
	<folder></folder>
	<filename>000078--3-_JPG_jpg.rf.e76f82cc3c7f3dd44fcd733acc645022.jpg</filename>
	<path>000078--3-_JPG_jpg.rf.e76f82cc3c7f3dd44fcd733acc645022.jpg</path>
	<source>
		<database>roboflow.ai</database>
	</source>
	<size>
		<width>416</width>
		<height>416</height>
		<depth>3</depth>
	</size>
	<segmented>0</segmented>
	<object>
		<name>karton</name>
		<pose>Unspecified</pose>
		<truncated>0</truncated>
		<difficult>0</difficult>
		<occluded>0</occluded>
		<bndbox>
			<xmin>153</xmin>
			<xmax>188</xmax>
			<ymin>8</ymin>
			<ymax>48</ymax>
		</bndbox>
	</object>
	<object>
		<name>plastik</name>
		<pose>Unspecified</pose>
		<truncated>0</truncated>
		<difficult>0</difficult>
		<occluded>0</occluded>
		<bndbox>
			<xmin>168</xmin>
			<xmax>196</xmax>
			<ymin>101</ymin>
			<ymax>139</ymax>
		</bndbox>
	</object>
	<object>
		<name>karton</name>
		<pose>Unspecified</pose>
		<truncated>0</truncated>
		<difficult>0</difficult>
		<occluded>0</occluded>
		<bndbox>
			<xmin>201</xmin>
			<xmax>230</xmax>
			<ymin>38</ymin>
			<ymax>74</ymax>
		</bndbox>
	</object>
	<object>
		<name>plastik</name>
		<pose>Unspecified</pose>
		<truncated>0</truncated>
		<difficult>0</difficult>
		<occluded>0</occluded>
		<bndbox>
			<xmin>181</xmin>
			<xmax>227</xmax>
			<ymin>50</ymin>
			<ymax>136</ymax>
		</bndbox>
	</object>
	<object>
		<name>plastik</name>
		<pose>Unspecified</pose>
		<truncated>0</truncated>
		<difficult>0</difficult>
		<occluded>0</occluded>
		<bndbox>
			<xmin>130</xmin>
			<xmax>188</xmax>
			<ymin>182</ymin>
			<ymax>207</ymax>
		</bndbox>
	</object>
	<object>
		<name>karton</name>
		<pose>Unspecified</pose>
		<truncated>0</truncated>
		<difficult>0</difficult>
		<occluded>0</occluded>
		<bndbox>
			<xmin>133</xmin>
			<xmax>157</xmax>
			<ymin>203</ymin>
			<ymax>259</ymax>
		</bndbox>
	</object>
	<object>
		<name>karton</name>
		<pose>Unspecified</pose>
		<truncated>0</truncated>
		<difficult>0</difficult>
		<occluded>0</occluded>
		<bndbox>
			<xmin>156</xmin>
			<xmax>178</xmax>
			<ymin>208</ymin>
			<ymax>252</ymax>
		</bndbox>
	</object>
	<object>
		<name>karton</name>
		<pose>Unspecified</pose>
		<truncated>0</truncated>
		<difficult>0</difficult>
		<occluded>0</occluded>
		<bndbox>
			<xmin>149</xmin>
			<xmax>164</xmax>
			<ymin>253</ymin>
			<ymax>273</ymax>
		</bndbox>
	</object>
	<object>
		<name>karton</name>
		<pose>Unspecified</pose>
		<truncated>0</truncated>
		<difficult>0</difficult>
		<occluded>0</occluded>
		<bndbox>
			<xmin>100</xmin>
			<xmax>234</xmax>
			<ymin>243</ymin>
			<ymax>415</ymax>
		</bndbox>
	</object>
	<object>
		<name>plastik</name>
		<pose>Unspecified</pose>
		<truncated>0</truncated>
		<difficult>0</difficult>
		<occluded>0</occluded>
		<bndbox>
			<xmin>44</xmin>
			<xmax>225</xmax>
			<ymin>316</ymin>
			<ymax>416</ymax>
		</bndbox>
	</object>
	<object>
		<name>plastik</name>
		<pose>Unspecified</pose>
		<truncated>0</truncated>
		<difficult>0</difficult>
		<occluded>0</occluded>
		<bndbox>
			<xmin>166</xmin>
			<xmax>349</xmax>
			<ymin>99</ymin>
			<ymax>373</ymax>
		</bndbox>
	</object>
	<object>
		<name>karton</name>
		<pose>Unspecified</pose>
		<truncated>0</truncated>
		<difficult>0</difficult>
		<occluded>0</occluded>
		<bndbox>
			<xmin>252</xmin>
			<xmax>268</xmax>
			<ymin>12</ymin>
			<ymax>42</ymax>
		</bndbox>
	</object>
	<object>
		<name>plastik</name>
		<pose>Unspecified</pose>
		<truncated>0</truncated>
		<difficult>0</difficult>
		<occluded>0</occluded>
		<bndbox>
			<xmin>276</xmin>
			<xmax>287</xmax>
			<ymin>89</ymin>
			<ymax>110</ymax>
		</bndbox>
	</object>
	<object>
		<name>plastik</name>
		<pose>Unspecified</pose>
		<truncated>0</truncated>
		<difficult>0</difficult>
		<occluded>0</occluded>
		<bndbox>
			<xmin>314</xmin>
			<xmax>416</xmax>
			<ymin>198</ymin>
			<ymax>387</ymax>
		</bndbox>
	</object>
	<object>
		<name>plastik</name>
		<pose>Unspecified</pose>
		<truncated>0</truncated>
		<difficult>0</difficult>
		<occluded>0</occluded>
		<bndbox>
			<xmin>272</xmin>
			<xmax>348</xmax>
			<ymin>322</ymin>
			<ymax>415</ymax>
		</bndbox>
	</object>
</annotation>
