<annotation>
	<folder></folder>
	<filename>000070--9-_jpg.rf.c8e5e1b0a48fdc7d6dd95ad95e8377d2.jpg</filename>
	<path>000070--9-_jpg.rf.c8e5e1b0a48fdc7d6dd95ad95e8377d2.jpg</path>
	<source>
		<database>roboflow.ai</database>
	</source>
	<size>
		<width>416</width>
		<height>416</height>
		<depth>3</depth>
	</size>
	<segmented>0</segmented>
	<object>
		<name>diger</name>
		<pose>Unspecified</pose>
		<truncated>0</truncated>
		<difficult>0</difficult>
		<occluded>0</occluded>
		<bndbox>
			<xmin>159</xmin>
			<xmax>174</xmax>
			<ymin>85</ymin>
			<ymax>145</ymax>
		</bndbox>
	</object>
</annotation>
